adafruit_register_spi/__init__.py
adafruit_register_spi/spi_bit.py
adafruit_register_spi/spi_bits.py
adafruit_circuitpython_register_spi-1.0.1.dist-info/LICENSE
adafruit_circuitpython_register_spi-1.0.1.dist-info/METADATA
adafruit_circuitpython_register_spi-1.0.1.dist-info/WHEEL
adafruit_circuitpython_register_spi-1.0.1.dist-info/top_level.txt
adafruit_circuitpython_register_spi-1.0.1.dist-info/RECORD
